core/__init__.py
core/constants.py
core/main.py
core/schemas.py
core/service.py
core/utils.py
fastapi_generator_util-1.0.8.dist-info/METADATA
fastapi_generator_util-1.0.8.dist-info/WHEEL
fastapi_generator_util-1.0.8.dist-info/entry_points.txt
fastapi_generator_util-1.0.8.dist-info/top_level.txt
fastapi_generator_util-1.0.8.dist-info/RECORD
