Metadata-Version: 2.1
Name: fastapi-generator-util
Version: 1.0.8
Summary: FastAPI code generator
Home-page: https://github.com/MulinEgor/fastapi-gen
Author: MulinEgor
Classifier: Programming Language :: Python :: 3
Classifier: License :: OSI Approved :: MIT License
Classifier: Operating System :: OS Independent
Requires-Python: >=3.9
Requires-Dist: questionary
Requires-Dist: pydantic
Requires-Dist: setuptools
Requires-Dist: wheel
Requires-Dist: twine
